adtk/__init__.py
adtk/_aggregator_base.py
adtk/_base.py
adtk/_detector_base.py
adtk/_transformer_base.py
adtk/_utils.py
adtk/aggregator/__init__.py
adtk/aggregator/_aggregator.py
adtk/data/__init__.py
adtk/data/_data.py
adtk/detector/__init__.py
adtk/detector/_detector_1d.py
adtk/detector/_detector_hd.py
adtk/metrics/__init__.py
adtk/metrics/_metrics.py
adtk/pipe/__init__.py
adtk/pipe/_pipe.py
adtk/transformer/__init__.py
adtk/transformer/_transformer_1d.py
adtk/transformer/_transformer_hd.py
adtk/visualization/__init__.py
adtk/visualization/_visualization.py
adtk-0.6.2.dist-info/LICENSE
adtk-0.6.2.dist-info/METADATA
adtk-0.6.2.dist-info/WHEEL
adtk-0.6.2.dist-info/top_level.txt
adtk-0.6.2.dist-info/RECORD
