Metadata-Version: 2.1
Name: adtk
Version: 0.6.2
Summary: A package for unsupervised time series anomaly detection
Home-page: https://github.com/arundo/adtk
Author: Arundo Analytics, Inc.
Maintainer: Tailai Wen
Maintainer-email: tailai.wen@arundo.com
License: Mozilla Public License 2.0 (MPL 2.0)
Keywords: anomaly detection,time series
Platform: UNKNOWN
Classifier: Development Status :: 5 - Production/Stable
Classifier: License :: OSI Approved :: Mozilla Public License 2.0 (MPL 2.0)
Classifier: Topic :: Scientific/Engineering
Classifier: Programming Language :: Python :: 3.5
Classifier: Programming Language :: Python :: 3.6
Classifier: Programming Language :: Python :: 3.7
Classifier: Programming Language :: Python :: 3.8
Classifier: Operating System :: POSIX :: Linux
Classifier: Operating System :: Unix
Classifier: Operating System :: MacOS
Classifier: Operating System :: Microsoft :: Windows
Requires-Python: >=3.5
Provides-Extra: doc
Provides-Extra: test
Provides-Extra: dev
